discord/__init__.py
discord/__main__.py
discord/abc.py
discord/activity.py
discord/appinfo.py
discord/asset.py
discord/audit_logs.py
discord/backoff.py
discord/calls.py
discord/channel.py
discord/client.py
discord/colour.py
discord/context_managers.py
discord/embeds.py
discord/emoji.py
discord/enums.py
discord/errors.py
discord/file.py
discord/flags.py
discord/gateway.py
discord/guild.py
discord/http.py
discord/integrations.py
discord/invite.py
discord/iterators.py
discord/member.py
discord/mentions.py
discord/message.py
discord/mixins.py
discord/object.py
discord/oggparse.py
discord/opus.py
discord/partial_emoji.py
discord/permissions.py
discord/player.py
discord/raw_models.py
discord/reaction.py
discord/relationship.py
discord/role.py
discord/shard.py
discord/state.py
discord/sticker.py
discord/team.py
discord/template.py
discord/user.py
discord/utils.py
discord/voice_client.py
discord/webhook.py
discord/widget.py
discord/bin/libopus-0.x64.dll
discord/bin/libopus-0.x86.dll
discord/ext/commands/__init__.py
discord/ext/commands/_types.py
discord/ext/commands/bot.py
discord/ext/commands/cog.py
discord/ext/commands/context.py
discord/ext/commands/converter.py
discord/ext/commands/cooldowns.py
discord/ext/commands/core.py
discord/ext/commands/errors.py
discord/ext/commands/help.py
discord/ext/commands/view.py
discord/ext/tasks/__init__.py
enddiscord/__init__.py
enddiscord/__main__.py
enddiscord/abc.py
enddiscord/activity.py
enddiscord/appinfo.py
enddiscord/asset.py
enddiscord/audit_logs.py
enddiscord/backoff.py
enddiscord/calls.py
enddiscord/channel.py
enddiscord/client.py
enddiscord/colour.py
enddiscord/context_managers.py
enddiscord/embeds.py
enddiscord/emoji.py
enddiscord/enums.py
enddiscord/errors.py
enddiscord/file.py
enddiscord/flags.py
enddiscord/gateway.py
enddiscord/guild.py
enddiscord/http.py
enddiscord/integrations.py
enddiscord/invite.py
enddiscord/iterators.py
enddiscord/member.py
enddiscord/mentions.py
enddiscord/message.py
enddiscord/mixins.py
enddiscord-1.0.1.dist-info/LICENSE
enddiscord-1.0.1.dist-info/METADATA
enddiscord-1.0.1.dist-info/WHEEL
enddiscord-1.0.1.dist-info/top_level.txt
enddiscord-1.0.1.dist-info/RECORD
